<?xml version="1.0" encoding="utf-8"?>
<ReturnMessage> 
		<MessageHead> 
				<messageFrom>Cus</messageFrom>  
				<messageFunc>Order</messageFunc>  
				<messageTime>2017-03-27 18:01:32</messageTime> 
		</MessageHead>  
		<OrderReturn> 
				<guid>578B57E2-315E-402E-B3B6-93CFF867A6F3</guid>  
				<ebpCode>350246049Y</ebpCode>  
				<ebcCode>350246049Y</ebcCode>  
				<orderNo>201703230340128</orderNo>  
				<returnStatus>2</returnStatus>  
				<returnTime>20170327175846</returnTime>  
				<returnInfo>订单新增申报成功[40021D81-013E-4309-8589-B5A38E4995B8]</returnInfo> 
		</OrderReturn> 
</ReturnMessage>
