<?xml version="1.0" encoding="utf-8"?>
<ReturnMessage> 
		<MessageHead> 
				<messageFrom>Cus</messageFrom>  
				<messageFunc>Order</messageFunc>  
				<messageTime>2017-03-24 18:03:31</messageTime> 
		</MessageHead>  
		<OrderReturn> 
				<guid>1411FC07-A146-424E-AD45-E8C653330E87</guid>  
				<ebpCode>350246049Y</ebpCode>  
				<ebcCode>350246049Y</ebcCode>  
				<orderNo>201703210310340</orderNo>  
				<returnStatus>2</returnStatus>  
				<returnTime>20170324180047</returnTime>  
				<returnInfo>订单新增申报成功[AEC80335-9D67-4D24-ACEA-109136136E3C]</returnInfo> 
		</OrderReturn> 
</ReturnMessage>
